dry_rest_permissions/__init__.py
dry_rest_permissions/generics.py
dry_rest_permissions-0.1.10.dist-info/DESCRIPTION.rst
dry_rest_permissions-0.1.10.dist-info/METADATA
dry_rest_permissions-0.1.10.dist-info/RECORD
dry_rest_permissions-0.1.10.dist-info/WHEEL
dry_rest_permissions-0.1.10.dist-info/metadata.json
dry_rest_permissions-0.1.10.dist-info/top_level.txt
