Metadata-Version: 2.0
Name: dry-rest-permissions
Version: 0.1.10
Summary: Rules based permissions for the Django Rest Framework
Home-page: https://github.com/Helioscene/dry-rest-permissions
Author: Heliosene, David B. Kaplan
Author-email: info@helioscene.com
License: BSD
Platform: UNKNOWN
Classifier: Development Status :: 5 - Production/Stable
Classifier: Environment :: Web Environment
Classifier: Framework :: Django
Classifier: Intended Audience :: Developers
Classifier: License :: OSI Approved :: BSD License
Classifier: Operating System :: OS Independent
Classifier: Natural Language :: English
Classifier: Programming Language :: Python :: 2.7
Classifier: Programming Language :: Python :: 3.4
Classifier: Programming Language :: Python :: 3.5
Classifier: Programming Language :: Python :: 3.6
Classifier: Topic :: Internet :: WWW/HTTP
